sf_dl/__init__.py
sf_dl/__main__.py
sf_dl/version.py
sf_dl-0.0.1.dist-info/METADATA
sf_dl-0.0.1.dist-info/WHEEL
sf_dl-0.0.1.dist-info/entry_points.txt
sf_dl-0.0.1.dist-info/licenses/LICENSE
sf_dl-0.0.1.dist-info/RECORD
