Metadata-Version: 2.4
Name: sf-dl
Version: 0.0.1
Summary: Python CLI module that allows to extract files from Salesforce using its REST API.
Project-URL: documentation, https://github.com/Pavel-Sushko/sf-dl#readme
Project-URL: repository, https://github.com/Pavel-Sushko/sf-dl
Project-URL: tracker, https://github.com/Pavel-Sushko/sf-dl/issues
Maintainer-email: Pavel Sushko <github@psushko.com>
License: MIT License
License-File: LICENSE
Keywords: salesforce
Classifier: Development Status :: 1 - Planning
Classifier: Environment :: Console
Classifier: Intended Audience :: Developers
Classifier: License :: OSI Approved :: MIT License
Classifier: Operating System :: OS Independent
Classifier: Programming Language :: Python
Classifier: Programming Language :: Python :: 3 :: Only
Classifier: Programming Language :: Python :: 3.12
Classifier: Programming Language :: Python :: 3.13
Classifier: Topic :: Utilities
Requires-Python: >=3.12
Requires-Dist: dotenv>=0.9.9
Requires-Dist: requests>=2.32.3
